pyxations/.gitignore
pyxations/.project
pyxations/.pydevproject
pyxations/__init__.py
pyxations/bids_formatting.py
pyxations/pre_processing.py
pyxations/utils.py
pyxations/analysis/generic.py
pyxations/analysis/visual_search.py
pyxations/export/__init__.py
pyxations/export/feather.py
pyxations/export/hdf.py
pyxations/formats/__init__.py
pyxations/formats/generic.py
pyxations/formats/eyelink/__init__.py
pyxations/formats/eyelink/bids.py
pyxations/formats/eyelink/parse.py
pyxations/formats/gazepoint/__init__.py
pyxations/formats/gazepoint/bids.py
pyxations/formats/gazepoint/parse.py
pyxations/formats/tobii/__init__.py
pyxations/formats/tobii/bids.py
pyxations/formats/tobii/parse.py
pyxations/formats/webgazer/__init__.py
pyxations/formats/webgazer/bids.py
pyxations/formats/webgazer/parse.py
pyxations/methods/__init__.py
pyxations/methods/eyemovement/REMoDNaV.py
pyxations/methods/eyemovement/__init__.py
pyxations/methods/eyemovement/engbert.py
pyxations/methods/eyemovement/eye_movement_detection.py
pyxations/visualization/__init__.py
pyxations/visualization/samples.py
pyxations/visualization/visualization.py
pyxations-0.2.10.dist-info/METADATA
pyxations-0.2.10.dist-info/WHEEL
pyxations-0.2.10.dist-info/licenses/LICENSE
pyxations-0.2.10.dist-info/RECORD
