Metadata-Version: 2.4
Name: pyxations
Version: 0.2.10
Summary: Pyxations: a Python-based toolbox to organize, parse, and analyse eye-movement data
Project-URL: Homepage, https://github.com/NeuroLIAA/pyxations
Author: NeuroLIAA
License: MIT
License-File: LICENSE
Requires-Python: >=3.10
Requires-Dist: blosc2
Requires-Dist: contourpy==1.3.1
Requires-Dist: cycler==0.12.1
Requires-Dist: cython==3.0.11
Requires-Dist: fonttools==4.55.3
Requires-Dist: iniconfig==2.0.0
Requires-Dist: kiwisolver==1.4.8
Requires-Dist: matplotlib==3.9.2
Requires-Dist: msgpack==1.1.0
Requires-Dist: multimatch-gaze==0.1.3
Requires-Dist: numexpr==2.10.2
Requires-Dist: numpy<2.0,>=1.24
Requires-Dist: opencv-python==4.9.0.80
Requires-Dist: packaging==24.2
Requires-Dist: pandas<2.2,>=1.5
Requires-Dist: patsy==1.0.1
Requires-Dist: pillow==11.1.0
Requires-Dist: pluggy==1.5.0
Requires-Dist: polars==1.26.0
Requires-Dist: py-cpuinfo==9.0.0
Requires-Dist: pyarrow==18.1.0
Requires-Dist: pyparsing==3.2.1
Requires-Dist: pytest==8.3.2
Requires-Dist: python-dateutil==2.9.0.post0
Requires-Dist: pytz==2024.2
Requires-Dist: remodnav==1.1.2
Requires-Dist: scipy==1.15.1
Requires-Dist: seaborn==0.13.2
Requires-Dist: six==1.17.0
Requires-Dist: statsmodels==0.14.4
Requires-Dist: tables
Requires-Dist: tqdm==4.67.1
Requires-Dist: tzdata==2024.2
Provides-Extra: docs
Requires-Dist: mkdocs; extra == 'docs'
Requires-Dist: mkdocs-material; extra == 'docs'
Requires-Dist: mkdocstrings[python]; extra == 'docs'
